nomenklatura/__init__.py
nomenklatura/cache.py
nomenklatura/cli.py
nomenklatura/conflicting_match.py
nomenklatura/db.py
nomenklatura/delta.py
nomenklatura/exceptions.py
nomenklatura/judgement.py
nomenklatura/kv.py
nomenklatura/py.typed
nomenklatura/settings.py
nomenklatura/util.py
nomenklatura/versions.py
nomenklatura/xref.py
nomenklatura/data/er-unstable.pkl
nomenklatura/data/regression-v1.pkl
nomenklatura/data/svm-v1.pkl
nomenklatura/enrich/__init__.py
nomenklatura/enrich/aleph.py
nomenklatura/enrich/common.py
nomenklatura/enrich/nominatim.py
nomenklatura/enrich/opencorporates.py
nomenklatura/enrich/openfigi.py
nomenklatura/enrich/permid.py
nomenklatura/enrich/wikidata.py
nomenklatura/enrich/yente.py
nomenklatura/index/__init__.py
nomenklatura/index/common.py
nomenklatura/index/entry.py
nomenklatura/index/index.py
nomenklatura/index/tokenizer.py
nomenklatura/matching/__init__.py
nomenklatura/matching/bench.py
nomenklatura/matching/compat.py
nomenklatura/matching/pairs.py
nomenklatura/matching/types.py
nomenklatura/matching/util.py
nomenklatura/matching/compare/__init__.py
nomenklatura/matching/compare/addresses.py
nomenklatura/matching/compare/countries.py
nomenklatura/matching/compare/dates.py
nomenklatura/matching/compare/gender.py
nomenklatura/matching/compare/identifiers.py
nomenklatura/matching/compare/names.py
nomenklatura/matching/compare/util.py
nomenklatura/matching/custom_v1/README.md
nomenklatura/matching/custom_v1/__init__.py
nomenklatura/matching/custom_v1/addresses.py
nomenklatura/matching/custom_v1/attributes.py
nomenklatura/matching/custom_v1/contacts.py
nomenklatura/matching/custom_v1/dates.py
nomenklatura/matching/custom_v1/identifiers.py
nomenklatura/matching/custom_v1/model.py
nomenklatura/matching/custom_v1/names.py
nomenklatura/matching/erun/__init__.py
nomenklatura/matching/erun/countries.py
nomenklatura/matching/erun/identifiers.py
nomenklatura/matching/erun/misc.py
nomenklatura/matching/erun/model.py
nomenklatura/matching/erun/names.py
nomenklatura_mpt-4.1.35.dist-info/METADATA
nomenklatura_mpt-4.1.35.dist-info/WHEEL
nomenklatura_mpt-4.1.35.dist-info/entry_points.txt
nomenklatura_mpt-4.1.35.dist-info/licenses/LICENSE
nomenklatura_mpt-4.1.35.dist-info/RECORD
