Metadata-Version: 2.4
Name: nomenklatura_mpt
Version: 4.1.35
Summary: Make record linkages in followthemoney data.
Project-URL: Documentation, https://github.com/opensanctions/nomenklatura/
Project-URL: Repository, https://github.com/opensanctions/nomenklatura.git
Project-URL: Issues, https://github.com/opensanctions/nomenklatura/issues
Author-email: OpenSanctions <info@opensanctions.org>
License: MIT
License-File: LICENSE
Classifier: Intended Audience :: Developers
Classifier: License :: OSI Approved :: MIT License
Classifier: Operating System :: OS Independent
Classifier: Programming Language :: Python :: 3.11
Classifier: Programming Language :: Python :: 3.12
Requires-Python: <3.14,>=3.11
Requires-Dist: click
Requires-Dist: fingerprints
Requires-Dist: followthemoney
Requires-Dist: lxml
Requires-Dist: pydantic
Requires-Dist: python-levenshtein<0.28.0,>=0.27.1
Requires-Dist: rich
Requires-Dist: rigour
Requires-Dist: scikit-learn
Requires-Dist: shortuuid
Requires-Dist: sqlalchemy
Requires-Dist: textual
Provides-Extra: dev
Requires-Dist: build; extra == 'dev'
Requires-Dist: bump2version; extra == 'dev'
Requires-Dist: coverage>=4.1; extra == 'dev'
Requires-Dist: fakeredis; extra == 'dev'
Requires-Dist: flake8>=2.6.0; extra == 'dev'
Requires-Dist: lxml-stubs; extra == 'dev'
Requires-Dist: mypy; extra == 'dev'
Requires-Dist: plyvel<2.0.0; extra == 'dev'
Requires-Dist: psycopg2-binary; extra == 'dev'
Requires-Dist: pytest; extra == 'dev'
Requires-Dist: pytest-cov; extra == 'dev'
Requires-Dist: redis<7.0.0,>5.0.0; extra == 'dev'
Requires-Dist: requests-mock; extra == 'dev'
Requires-Dist: twine; extra == 'dev'
Requires-Dist: types-pyyaml; extra == 'dev'
Requires-Dist: types-redis; extra == 'dev'
Requires-Dist: types-requests; extra == 'dev'
Requires-Dist: types-setuptools; extra == 'dev'
Requires-Dist: wheel>=0.29.0; extra == 'dev'
Provides-Extra: leveldb
Requires-Dist: plyvel<2.0.0; extra == 'leveldb'
Provides-Extra: redis
Requires-Dist: redis<7.0.0,>5.0.0; extra == 'redis'
